bsci_file_library/__init__.py
bsci_file_library-0.0.1.dist-info/METADATA
bsci_file_library-0.0.1.dist-info/WHEEL
bsci_file_library-0.0.1.dist-info/top_level.txt
bsci_file_library-0.0.1.dist-info/RECORD
